commonroad_clcs/__init__.py
commonroad_clcs/clcs.py
commonroad_clcs/config.py
commonroad_clcs/pycrccosy.cpython-310-x86_64-linux-gnu.so
commonroad_clcs/util.py
commonroad_clcs/helper/__init__.py
commonroad_clcs/helper/evaluation.py
commonroad_clcs/helper/interpolation.py
commonroad_clcs/helper/smoothing.py
commonroad_clcs/helper/visualization.py
commonroad_clcs/ref_path_processing/__init__.py
commonroad_clcs/ref_path_processing/factory.py
commonroad_clcs/ref_path_processing/implementation.py
commonroad_clcs/ref_path_processing/processor.py
commonroad_clcs.libs/libgomp-a34b3233.so.1.0.0
commonroad_clcs-2025.2.0.dist-info/METADATA
commonroad_clcs-2025.2.0.dist-info/WHEEL
commonroad_clcs-2025.2.0.dist-info/RECORD
commonroad_clcs-2025.2.0.dist-info/licenses/LICENSE.txt
