Metadata-Version: 2.1
Name: commonroad-clcs
Version: 2025.2.0
Summary: Curvilinear (Frenet) Coordinate System for motion planning.
Keywords: autonomous vehicles,automated driving,motion planning,frenet coordinates,commonroad
Author-Email: Cyber-Physical Systems Group - Technical University of Munich <commonroad@lists.lrz.de>
License: BSD 3-Clause License
Classifier: Programming Language :: C++
Classifier: Programming Language :: Python :: 3.10
Classifier: Programming Language :: Python :: 3.11
Classifier: Programming Language :: Python :: 3.12
Classifier: Programming Language :: Python :: 3.13
Classifier: License :: OSI Approved :: BSD License
Classifier: Operating System :: POSIX :: Linux
Project-URL: Homepage, https://commonroad.in.tum.de/tools/commonroad-clcs
Project-URL: Documentation, https://commonroad.in.tum.de/docs/commonroad-clcs/
Project-URL: Source, https://github.com/CommonRoad/commonroad-curvilinear-coordinate-system
Requires-Python: <3.14,>=3.10
Requires-Dist: commonroad-io>=2023.1
Requires-Dist: matplotlib>=3.3.3
Requires-Dist: numpy>=1.19.2
Requires-Dist: omegaconf>=2.1.1
Requires-Dist: scipy>=1.4.1
Requires-Dist: shapely>=2.0.0
Requires-Dist: osqp~=0.6.5
Provides-Extra: test
Requires-Dist: pytest>=3.8.0; extra == "test"
Requires-Dist: parameterized~=0.9.0; extra == "test"
Provides-Extra: docs
Requires-Dist: mkdocs<2.0.0,>=1.6.1; extra == "docs"
Requires-Dist: mkdocstrings-python<2.0.0,>=1.8.0; extra == "docs"
Requires-Dist: mkdocs-material<10.0.0,>=9.5.10; extra == "docs"
Requires-Dist: mkdoxy~=1.2.4; extra == "docs"
Provides-Extra: build
Requires-Dist: scikit-build-core~=0.11.0; extra == "build"
Requires-Dist: nanobind~=2.2.0; extra == "build"
Requires-Dist: pathspec>=0.12.1; extra == "build"
Requires-Dist: pyproject-metadata>=0.7.1; extra == "build"
Requires-Dist: typing_extensions~=4.12.2; extra == "build"
Requires-Dist: cmake<4.0,>=3.24; extra == "build"
